xontrib/abbrevs.py
xontrib_abbrevs-0.1.0.dist-info/LICENSE
xontrib_abbrevs-0.1.0.dist-info/METADATA
xontrib_abbrevs-0.1.0.dist-info/WHEEL
xontrib_abbrevs-0.1.0.dist-info/top_level.txt
xontrib_abbrevs-0.1.0.dist-info/RECORD
