Metadata-Version: 2.1
Name: xontrib-abbrevs
Version: 0.1.0
Summary: Expands input words as you type in xonsh shell.
Author-email: xontrib-abbrevs <no@no.no>
License: MIT License
Project-URL: Homepage, https://github.com/xonsh/xontrib-abbrevs
Project-URL: Documentation, https://github.com/xonsh/xontrib-abbrevs/blob/master/README.md
Project-URL: Code, https://github.com/xonsh/xontrib-abbrevs
Project-URL: Issue tracker, https://github.com/xonsh/xontrib-abbrevs/issues
Platform: any
Classifier: Programming Language :: Python :: 3
Classifier: License :: OSI Approved :: MIT License
Classifier: Operating System :: OS Independent
Classifier: Topic :: System :: Shells
Classifier: Topic :: System :: System Shells
Classifier: Topic :: Terminals
Requires-Python: >=3.10
License-File: LICENSE
Requires-Dist: xonsh >=0.17
Requires-Dist: prompt-toolkit
Provides-Extra: dev
Requires-Dist: pytest >=7.0 ; extra == 'dev'
